python_qa/__init__.py
python_qa/conftest.py
python_qa/decorators/__init__.py
python_qa/decorators/decorators.py
python_qa/doubler/__init__.py
python_qa/doubler/stub/__init__.py
python_qa/doubler/stub/base.py
python_qa/logging/__init__.py
python_qa/logging/logging.py
python_qa/pytest/__init__.py
python_qa/pytest/rerun.py
python_qa/pytest/validations.py
python_qa/requests/__init__.py
python_qa/requests/hooks.py
python_qa/service/__init__.py
python_qa/service/base_service.py
python_qa/types/__init__.py
python_qa/types/base_types.py
python_qa/ui/__init__.py
python_qa/ui/playwright/__init__.py
python_qa/ui/selenium/__init__.py
python_qa/ui/selenium/base_driver.py
python_qa/ui/selenium/base_page.py
python_qa/ui/selenium/expected_conditions.py
python_qa/ui/selenium/reports.py
python_qa/utils/__init__.py
python_qa/utils/classes.py
python_qa/utils/data.py
python_qa/utils/files.py
python_qa/utils/func.py
python_qa/utils/iterable.py
python_qa/utils/random.py
python_qa/utils/requests.py
python_qa/utils/string.py
python_qa/utils/wait.py
python_qa-0.0.8.dist-info/LICENSE
python_qa-0.0.8.dist-info/METADATA
python_qa-0.0.8.dist-info/WHEEL
python_qa-0.0.8.dist-info/entry_points.txt
python_qa-0.0.8.dist-info/top_level.txt
python_qa-0.0.8.dist-info/RECORD
